{"imagePath":"09_strongWolf_tex.png","width":512,"name":"09_strongWolf","SubTexture":[{"x":1,"y":153,"width":150,"name":"shadow","height":90},{"x":415,"y":1,"width":39,"name":"hand2-1","height":32},{"x":483,"y":33,"width":28,"name":"hand2-3","height":24},{"x":322,"y":1,"width":39,"name":"hand2-2","height":52},{"x":202,"y":204,"width":41,"name":"tail","height":34},{"x":254,"y":1,"width":66,"name":"body","height":75},{"x":402,"y":35,"width":33,"name":"leg2-3","height":21},{"x":132,"y":110,"width":19,"name":"leg2-2","height":24},{"x":369,"y":28,"width":31,"name":"leg2-1","height":35},{"x":153,"y":204,"width":47,"name":"hip","height":42},{"x":456,"y":1,"width":32,"name":"leg1-3","height":30},{"x":456,"y":33,"width":25,"name":"leg1-2","height":28},{"x":473,"y":182,"width":26,"name":"leg1-1","height":42},{"x":322,"y":55,"width":45,"name":"hand1-1","height":43},{"x":473,"y":226,"width":35,"name":"hand1-3","height":29},{"x":247,"y":192,"width":52,"name":"hand1-2","height":63},{"x":411,"y":110,"width":79,"name":"neck","height":70},{"x":490,"y":1,"width":17,"name":"ear2","height":27},{"x":247,"y":110,"width":82,"name":"head","height":80},{"x":301,"y":192,"width":23,"name":"ear1","height":32},{"height":78,"y":110,"frameWidth":83,"frameX":-2,"frameHeight":83,"frameY":-2,"width":78,"name":"circle","x":331},{"height":35,"y":190,"frameWidth":148,"frameX":-4,"frameHeight":38,"frameY":-1,"width":140,"name":"piece01","x":331},{"x":1,"y":1,"width":129,"name":"vortex01","height":150},{"x":132,"y":1,"width":120,"name":"vortex02","height":107},{"x":153,"y":110,"width":92,"name":"glow-circle","height":92},{"height":27,"y":78,"frameWidth":54,"frameX":0,"frameHeight":27,"frameY":0,"width":54,"name":"battleBufferEffect1_10001","x":254},{"height":25,"y":227,"frameWidth":50,"frameX":0,"frameHeight":26,"frameY":0,"width":50,"name":"battleBufferEffect1_10003","x":410},{"x":363,"y":1,"width":50,"name":"battleBufferEffect1_10004","height":25},{"height":26,"y":227,"frameWidth":51,"frameX":0,"frameHeight":27,"frameY":0,"width":51,"name":"battleBufferEffect1_10005","x":357},{"x":301,"y":227,"width":54,"name":"battleBufferEffect1_10002","height":27}],"height":256}